wechaty_plugin_contrib/__init__.py
wechaty_plugin_contrib/config.py
wechaty_plugin_contrib/exception.py
wechaty_plugin_contrib/message_controller.py
wechaty_plugin_contrib/utils.py
wechaty_plugin_contrib/validate_plugin.py
wechaty_plugin_contrib/version.py
wechaty_plugin_contrib/contrib/__init__.py
wechaty_plugin_contrib/contrib/api_plugin.py
wechaty_plugin_contrib/contrib/ding_dong_plugin.py
wechaty_plugin_contrib/contrib/health_checker_plugin.py
wechaty_plugin_contrib/contrib/httpplugin.py
wechaty_plugin_contrib/contrib/info_downloader.py
wechaty_plugin_contrib/contrib/info_logger.py
wechaty_plugin_contrib/contrib/message_forwarder_plugin.py
wechaty_plugin_contrib/contrib/on_friendship_plugin.py
wechaty_plugin_contrib/contrib/on_room_join_plugin.py
wechaty_plugin_contrib/contrib/rasa_rest_plugin.py
wechaty_plugin_contrib/contrib/rss_plugin.py
wechaty_plugin_contrib/contrib/send_message_plugin.py
wechaty_plugin_contrib/contrib/welcome_plugin.py
wechaty_plugin_contrib/contrib/auto_reply_plugin/__init__.py
wechaty_plugin_contrib/contrib/auto_reply_plugin/plugin.py
wechaty_plugin_contrib/contrib/chat_history_plugin/__init__.py
wechaty_plugin_contrib/contrib/chat_history_plugin/data.py
wechaty_plugin_contrib/contrib/chat_history_plugin/plugin.py
wechaty_plugin_contrib/contrib/github_webhook_plugin/__init__.py
wechaty_plugin_contrib/contrib/github_webhook_plugin/options.py
wechaty_plugin_contrib/contrib/github_webhook_plugin/plugin.py
wechaty_plugin_contrib/contrib/gitlab_event_plugin/__init__.py
wechaty_plugin_contrib/contrib/gitlab_event_plugin/options.py
wechaty_plugin_contrib/contrib/gitlab_event_plugin/plugin.py
wechaty_plugin_contrib/contrib/health_checker_plugin/__init__.py
wechaty_plugin_contrib/contrib/health_checker_plugin/plugin.py
wechaty_plugin_contrib/contrib/health_checker_plugin/watch_tower.py
wechaty_plugin_contrib/contrib/paddlespeech_plugin/__init__.py
wechaty_plugin_contrib/contrib/paddlespeech_plugin/plugin.py
wechaty_plugin_contrib-0.0.25.dist-info/LICENSE
wechaty_plugin_contrib-0.0.25.dist-info/METADATA
wechaty_plugin_contrib-0.0.25.dist-info/WHEEL
wechaty_plugin_contrib-0.0.25.dist-info/top_level.txt
wechaty_plugin_contrib-0.0.25.dist-info/RECORD
