Metadata-Version: 2.1
Name: wechaty-plugin-contrib
Version: 0.0.25
Summary: Python Wechaty Plugin Contrib is a repo which store the pupular wechaty contrib
Home-page: https://github.com/wechaty/python-wechaty-plugin-contrib
Author: wj-Mcat (吴京京)
Author-email: 1435130236@qq.com
License: Apache-2.0
Classifier: Programming Language :: Python :: 3.7
Classifier: License :: OSI Approved :: Apache Software License
Classifier: Operating System :: OS Independent
License-File: LICENSE
Requires-Dist: wechaty (>=0.10.2)
Requires-Dist: jieba
Requires-Dist: aiohttp
Requires-Dist: requests
Requires-Dist: sqlalchemy
Requires-Dist: apscheduler
Requires-Dist: feedparser
